zipint/README.MD
zipint/__init__.py
zipint/requirements.txt
zipint/thirdparty.json
zipint-0.10.dist-info/LICENSE.rst
zipint-0.10.dist-info/METADATA
zipint-0.10.dist-info/WHEEL
zipint-0.10.dist-info/top_level.txt
zipint-0.10.dist-info/RECORD
