Metadata-Version: 2.1
Name: zipint
Version: 0.10
Summary: Efficient compression and decompression of unsigned integer arrays using binary representation.
Home-page: https://github.com/hansalemaos/zipint
Author: Johannes Fischer
Author-email: aulasparticularesdealemaosp@gmail.com
License: MIT
Keywords: zip,int
Classifier: Development Status :: 4 - Beta
Classifier: Programming Language :: Python :: 3 :: Only
Classifier: Programming Language :: Python :: 3.10
Classifier: Topic :: Software Development :: Libraries :: Python Modules
Classifier: Topic :: Utilities
License-File: LICENSE.rst
Requires-Dist: numpy
